airtable_pack/__init__.py
airtable_pack/client.py
airtable_pack/operations/__init__.py
airtable_pack/operations/create_record.py
airtable_pack/operations/delete_record.py
airtable_pack/operations/get_record.py
airtable_pack/operations/update_fields.py
airtable_pack/operations/update_record.py
airtable_pack/restaurant/__init__.py
airtable_pack/restaurant/orders.py
airtable_pack-0.0.9.dist-info/LICENSE
airtable_pack-0.0.9.dist-info/METADATA
airtable_pack-0.0.9.dist-info/WHEEL
airtable_pack-0.0.9.dist-info/top_level.txt
airtable_pack-0.0.9.dist-info/RECORD
